artcoloranalyzer/__init__.py
artcoloranalyzer/analyzer.py
artcoloranalyzer/object_specific_hue_adjustment.py
artcoloranalyzer/overall_hue_adjustment.py
tests/__init__.py
tests/test_analyzer.py
ArtColorAnalyzer_Hue_Adjustment_Tool-0.1.0.dist-info/LICENSE
ArtColorAnalyzer_Hue_Adjustment_Tool-0.1.0.dist-info/METADATA
ArtColorAnalyzer_Hue_Adjustment_Tool-0.1.0.dist-info/WHEEL
ArtColorAnalyzer_Hue_Adjustment_Tool-0.1.0.dist-info/entry_points.txt
ArtColorAnalyzer_Hue_Adjustment_Tool-0.1.0.dist-info/top_level.txt
ArtColorAnalyzer_Hue_Adjustment_Tool-0.1.0.dist-info/RECORD
