Metadata-Version: 2.1
Name: ArtColorAnalyzer-Hue-Adjustment-Tool
Version: 0.1.0
Summary: A tool for overall and object-specific hue adjustment in images.
Home-page: https://github.com/aoo0703/ArtColorAnalyzer-Hue-Adjustment-Tool.git
Author: aoo0703
Author-email: s2222069@stu.musashino-u.ac.jp
Classifier: Programming Language :: Python :: 3
Classifier: License :: OSI Approved :: MIT License
Classifier: Operating System :: OS Independent
Requires-Python: >=3.6
License-File: LICENSE
Requires-Dist: opencv-python-headless
Requires-Dist: numpy
Requires-Dist: Pillow
Requires-Dist: scikit-image
